setup.py
py3gearman/__init__.py
py3gearman/admin_client.py
py3gearman/admin_client_handler.py
py3gearman/client.py
py3gearman/client_handler.py
py3gearman/command_handler.py
py3gearman/compat.py
py3gearman/connection.py
py3gearman/connection_manager.py
py3gearman/constants.py
py3gearman/errors.py
py3gearman/job.py
py3gearman/protocol.py
py3gearman/setup.py
py3gearman/util.py
py3gearman/worker.py
py3gearman/worker_handler.py
py3gearman.egg-info/PKG-INFO
py3gearman.egg-info/SOURCES.txt
py3gearman.egg-info/dependency_links.txt
py3gearman.egg-info/top_level.txt