Metadata-Version: 1.1
Name: py3gearman
Version: 0.2.0
Summary: Gearman API - Client, worker, and admin client interfaces for Python3
Home-page: https://github.com/shuto-S/py3gearman
Author: Shuto Shimabukuro
Author-email: shuto4192@gmail.com
License: UNKNOWN
Platform: UNKNOWN
Classifier: Development Status :: 5 - Production/Stable
Classifier: Intended Audience :: Developers
Classifier: Operating System :: OS Independent
Classifier: Programming Language :: Python
Classifier: Programming Language :: Python :: 3.5
Classifier: Topic :: Software Development :: Libraries :: Python Modules
